{
  "__id__": "avatar",
  "name": "头像",
  "desc": "Avatar 组件可以用来代表人物或对象， 支持使用图片、图标或者文字作为 Avatar。",
  "tag": "el-avatar",
  "tagIcon": "avatar",
  "layouts": [
    "rawItem"
  ],
  "document": "https://element-plus.org/zh-CN/component/avatar.html",
  "attributes": {
    "icon": {
      "label": "图标",
      "title": "设置 Avatar 的图标类型，具体参考 Icon 组件",
      "types": [
        {
          "name": "string",
          "tag": "icon-chooser"
        }
      ]
    },
    "size": {
      "label": "大小",
      "title": "Avatar 大小",
      "types": [
        {
          "name": "number",
          "tag": "el-input-number",
          "default": 50
        },
        {
          "name": "enum",
          "tag": "el-radio-group",
          "config": {
            "optionType": "button"
          },
          "options": [
            {
              "label": "large",
              "value": "large"
            },
            {
              "label": "default",
              "value": "default"
            },
            {
              "label": "small",
              "value": "small"
            }
          ]
        }
      ],
      "default": "default"
    },
    "shape": {
      "label": "形状",
      "title": "Avatar 形状",
      "types": [
        {
          "name": "enum",
          "tag": "el-radio-group",
          "config": {
            "optionType": "button"
          },
          "options": [
            {
              "label": "circle",
              "value": "circle"
            },
            {
              "label": "square",
              "value": "square"
            }
          ]
        }
      ],
      "default": "circle"
    },
    "src": {
      "label": "图片源地址",
      "title": "Avatar 图片的源地址",
      "types": [
        {
          "name": "string",
          "tag": "el-input",
          "props": {
            "clearable": true
          }
        }
      ]
    },
    "src-set": {
      "label": "图片 Avatar 的原生 srcset 属性",
      "title": "图片 Avatar 的原生 <code>srcset</code> 属性",
      "types": [
        {
          "name": "string",
          "tag": "el-input",
          "props": {
            "clearable": true
          }
        }
      ]
    },
    "alt": {
      "label": "alt属性",
      "title": "图片 Avatar 的原生 <code>alt</code> 属性",
      "types": [
        {
          "name": "string",
          "tag": "el-input",
          "props": {
            "clearable": true
          }
        }
      ]
    },
    "fit": {
      "label": "适应容器",
      "title": "当展示类型为图片的时候，设置图片如何适应容器",
      "types": [
        {
          "name": "enum",
          "tag": "el-select",
          "options": [
            {
              "label": "fill",
              "value": "fill"
            },
            {
              "label": "contain",
              "value": "contain"
            },
            {
              "label": "cover",
              "value": "cover"
            },
            {
              "label": "none",
              "value": "none"
            },
            {
              "label": "scale-down",
              "value": "scale-down"
            }
          ]
        }
      ],
      "default": "cover"
    }
  },
  "slots": [
    {
      "name": "default",
      "title": "自定义头像展示内容"
    }
  ],
  "events": [
    {
      "name": "error",
      "title": "图片加载失败时触发",
      "type": "function",
      "details": "(e: Event) => void"
    }
  ]
}